README.md
setup.cfg
setup.py
priorityscheduler/__init__.py
priorityscheduler/job.py
priorityscheduler/priority_queue.py
priorityscheduler.egg-info/PKG-INFO
priorityscheduler.egg-info/SOURCES.txt
priorityscheduler.egg-info/dependency_links.txt
priorityscheduler.egg-info/top_level.txt