Metadata-Version: 1.1
Name: priorityscheduler
Version: 0.2
Summary: Priority Queue to schedule custom jobs
Home-page: https://github.com/TomOrth/Priority-Queue-Job-Scheduler
Author: Tom Orth
Author-email: torth212@gmail.com
License: MIT
Download-URL: https://github.com/atf1999/executioner/tarball/0.2
Platform: UNKNOWN
